COPYING
MANIFEST.in
README.rst
setup.py
sqlize_pg/__init__.py
sqlize_pg/builder.py
sqlize_pg.egg-info/PKG-INFO
sqlize_pg.egg-info/SOURCES.txt
sqlize_pg.egg-info/dependency_links.txt
sqlize_pg.egg-info/top_level.txt